crate/theme/__init__.py
crate/theme/rtd/__init__.py
crate/theme/rtd/sidebartoc.py
crate/theme/rtd/conf/__init__.py
crate/theme/rtd/conf/cloud.py
crate/theme/rtd/conf/cloud_cli.py
crate/theme/rtd/conf/crate_admin_ui.py
crate/theme/rtd/conf/crate_clients_tools.py
crate/theme/rtd/conf/crate_crash.py
crate/theme/rtd/conf/crate_howtos.py
crate/theme/rtd/conf/crate_reference.py
crate/theme/rtd/conf/crate_tutorials.py
crate/theme/rtd/conf/cratedb_guide.py
crate/theme/rtd/conf/dbal.py
crate/theme/rtd/conf/doing_docs.py
crate/theme/rtd/conf/furo.py
crate/theme/rtd/conf/jdbc.py
crate/theme/rtd/conf/npgsql.py
crate/theme/rtd/conf/pdo.py
crate/theme/rtd/conf/python.py
crate/theme/rtd/conf/sql_99.py
crate/theme/rtd/conf/sqlalchemy_cratedb.py
crate/theme/rtd/conf/theme.py
crate/theme/rtd/crate/base.html
crate/theme/rtd/crate/globaltoc.html
crate/theme/rtd/crate/layout_legacy.html
crate/theme/rtd/crate/localtoc.html
crate/theme/rtd/crate/navbarsearchbox.html
crate/theme/rtd/crate/navbartoc.html
crate/theme/rtd/crate/page.html
crate/theme/rtd/crate/relations.html
crate/theme/rtd/crate/search.html
crate/theme/rtd/crate/searchbox.html
crate/theme/rtd/crate/searchresults.html
crate/theme/rtd/crate/settings.html
crate/theme/rtd/crate/sidebar.html
crate/theme/rtd/crate/sidebartoc.html
crate/theme/rtd/crate/sourcelink.html
crate/theme/rtd/crate/theme.conf
crate/theme/rtd/crate/components/github_feedback_compact.html
crate/theme/rtd/crate/components/github_feedback_full.html
crate/theme/rtd/crate/components/github_feedback_full.js
crate/theme/rtd/crate/components/github_keynav.js
crate/theme/rtd/crate/components/related-pages.html
crate/theme/rtd/crate/components/toggle-sidebar-primary.html
crate/theme/rtd/crate/components/toggle-sidebar-secondary.html
crate/theme/rtd/crate/components/version_chooser.html
crate/theme/rtd/crate/directives/__init__.py
crate/theme/rtd/crate/directives/stepper.py
crate/theme/rtd/crate/partials/_head_css_variables.html
crate_docs_theme-0.47.0.dist-info/licenses/LICENSE
crate_docs_theme-0.47.0.dist-info/licenses/NOTICE
crate_docs_theme-0.47.0.dist-info/METADATA
crate_docs_theme-0.47.0.dist-info/WHEEL
crate_docs_theme-0.47.0.dist-info/top_level.txt
crate_docs_theme-0.47.0.dist-info/RECORD
