Metadata-Version: 2.4
Name: crate-docs-theme
Version: 0.47.0
Summary: CrateDB Documentation Theme
Home-page: https://github.com/crate/crate-docs-theme
Author: Crate.IO GmbH
Author-email: office@crate.io
License: Apache License 2.0
Keywords: cratedb docs sphinx readthedocs
Classifier: Intended Audience :: Developers
Classifier: Operating System :: OS Independent
Classifier: Programming Language :: Python
Classifier: Programming Language :: Python :: 3
Classifier: Programming Language :: Python :: 3.9
Classifier: Programming Language :: Python :: 3.10
Classifier: Programming Language :: Python :: 3.11
Classifier: Programming Language :: Python :: 3.12
Classifier: Programming Language :: Python :: 3.13
Classifier: Programming Language :: Python :: 3.14
Classifier: Topic :: Software Development :: Documentation
Requires-Python: >=3.9
License-File: LICENSE
License-File: NOTICE
Requires-Dist: furo==2025.12.19
Requires-Dist: jinja2<4,>=3
Requires-Dist: jupysql<0.12
Requires-Dist: myst-nb<1.4
Requires-Dist: myst-parser[linkify]<5
Requires-Dist: snowballstemmer<4
Requires-Dist: sphinx<9,>=7.1
Requires-Dist: sphinx-basic-ng==1.0.0b2
Requires-Dist: sphinx-copybutton<1,>=0.3.1
Requires-Dist: sphinx-design-elements==0.4.1
Requires-Dist: sphinx-inline-tabs
Requires-Dist: sphinx-sitemap<2.10.0
Requires-Dist: sphinx-togglebutton<1
Requires-Dist: sphinxext.opengraph<1,>=0.4
Requires-Dist: sphinxcontrib-mermaid<2
Requires-Dist: sphinxcontrib-plantuml<1,>=0.21
Requires-Dist: sphinxcontrib-youtube<2
Dynamic: author
Dynamic: author-email
Dynamic: classifier
Dynamic: description
Dynamic: description-content-type
Dynamic: home-page
Dynamic: keywords
Dynamic: license
Dynamic: license-file
Dynamic: requires-dist
Dynamic: requires-python
Dynamic: summary
